flawfinder.py
flawfinder-2.0.19.data/data/share/man/man1/flawfinder.1.gz
flawfinder-2.0.19.dist-info/COPYING
flawfinder-2.0.19.dist-info/METADATA
flawfinder-2.0.19.dist-info/WHEEL
flawfinder-2.0.19.dist-info/entry_points.txt
flawfinder-2.0.19.dist-info/top_level.txt
flawfinder-2.0.19.dist-info/zip-safe
flawfinder-2.0.19.dist-info/RECORD
